iTude/__init__.py
iTude/z_core.py
iTude/z_main.py
iTude/aopom/__init__.py
iTude/aopom/chuanbei/__init__.py
iTude/aopom/chuanbei/base/__init__.py
iTude/aopom/chuanbei/base/pageobject_.py
iTude/aopom/chuanbei/testcase/__init__.py
iTude/aopom/chuanbei/visit/__init__.py
iTude/aopom/chuanbei/visit/flowobject_.py
iTude/aopom/director/__init__.py
iTude/aopom/director/director_.py
iTude/aopom/director/director_[Template]_.py
iTude/aopom/director/hbqdirector_.py
iTude/aopom/director/liyuandirector_.py
iTude/aopom/director/misc_.py
iTude/aopom/director/reflection_deco_.py
iTude/aopom/director/refractor_.py
iTude/aopom/director/original_/liyuandirector_20210622_.py
iTude/aopom/director/original_/refractor_sub_.py
iTude-0.2.4.dist-info/LICENSE.txt
iTude-0.2.4.dist-info/METADATA
iTude-0.2.4.dist-info/WHEEL
iTude-0.2.4.dist-info/top_level.txt
iTude-0.2.4.dist-info/RECORD
