Metadata-Version: 2.1
Name: iTude
Version: 0.2.4
Summary: A Tool for Attitude Longitude of Site (Mute)
Home-page: https://github.com/chenchaotsun/scripts
Author: Chaoqun Chen
Author-email: chen.chaoqun.ext@99cloud.net
License: GNU General Public License v3.0
Project-URL: Bug Tracker, https://github.com/pypa/sampleproject/issues
Keywords: attitude_longitude
Platform: UNKNOWN
Classifier: Programming Language :: Python :: 3
Classifier: License :: OSI Approved :: GNU General Public License v3 (GPLv3)
Classifier: Operating System :: OS Independent
Requires-Python: >=3.6
License-File: LICENSE.txt
